hoptex/__init__.py
hoptex/configs.py
hoptex/decorator.py
hoptex/hop_screen.py
hoptex/py.typed
hoptex/utils.py
hoptex-0.2.0.dist-info/LICENSE
hoptex-0.2.0.dist-info/METADATA
hoptex-0.2.0.dist-info/WHEEL
hoptex-0.2.0.dist-info/RECORD
