Metadata-Version: 2.1
Name: hoptex
Version: 0.2.0
Summary: Hoptex is Textual plugin that allows you to focus widgets fast!
Home-page: https://github.com/Cvaniak/Hoptex
Author: Cvaniak
Author-email: igna.cwaniak@gmail.com
Requires-Python: >=3.7
Classifier: Programming Language :: Python :: 3
Classifier: Programming Language :: Python :: 3.7
Classifier: Programming Language :: Python :: 3.8
Classifier: Programming Language :: Python :: 3.9
Classifier: Programming Language :: Python :: 3.10
Classifier: Programming Language :: Python :: 3.11
Requires-Dist: textual (>=0.21.0)
Project-URL: Repository, https://github.com/Cvaniak/Hoptex
